azure/mgmt/qumulo/__init__.py
azure/mgmt/qumulo/_configuration.py
azure/mgmt/qumulo/_patch.py
azure/mgmt/qumulo/_qumulo_mgmt_client.py
azure/mgmt/qumulo/_serialization.py
azure/mgmt/qumulo/_version.py
azure/mgmt/qumulo/py.typed
azure/mgmt/qumulo/aio/__init__.py
azure/mgmt/qumulo/aio/_configuration.py
azure/mgmt/qumulo/aio/_patch.py
azure/mgmt/qumulo/aio/_qumulo_mgmt_client.py
azure/mgmt/qumulo/aio/operations/__init__.py
azure/mgmt/qumulo/aio/operations/_file_systems_operations.py
azure/mgmt/qumulo/aio/operations/_operations.py
azure/mgmt/qumulo/aio/operations/_patch.py
azure/mgmt/qumulo/models/__init__.py
azure/mgmt/qumulo/models/_models_py3.py
azure/mgmt/qumulo/models/_patch.py
azure/mgmt/qumulo/models/_qumulo_mgmt_client_enums.py
azure/mgmt/qumulo/operations/__init__.py
azure/mgmt/qumulo/operations/_file_systems_operations.py
azure/mgmt/qumulo/operations/_operations.py
azure/mgmt/qumulo/operations/_patch.py
azure_mgmt_qumulo-2.0.0.dist-info/LICENSE
azure_mgmt_qumulo-2.0.0.dist-info/METADATA
azure_mgmt_qumulo-2.0.0.dist-info/WHEEL
azure_mgmt_qumulo-2.0.0.dist-info/top_level.txt
azure_mgmt_qumulo-2.0.0.dist-info/RECORD
